[
    {
        "Friday": "10:00~21:00",
        "Monday": "10:00~21:00",
        "Saturday": "10:00~21:00",
        "Sunday": "10:00~21:00",
        "Thursday": "10:00~21:00",
        "Tuesday": "10:00~21:00",
        "Wednesday": "10:00~21:00",
        "exam_part": "",
        "holiday": "10:00~21:00",
        "instit_kind": "약국",
        "instit_nm": "트레이더스약국",
        "lat": "35.18408381",
        "lng": "129.0802078",
        "medical_instit_kind": "응급의료기관이외",
        "organ_loc": "이마트 트레이더스 내 위치",
        "regist_dt": "2021-02-10",
        "street_nm_addr": "부산광역시 연제구 좌수영로 241, 지하3층 (연산동)",
        "sunday_oper_week": "1 2 3 4 5",
        "tel": "051-505-2680",
        "update_dt": "2021-02-10",
        "zip_code": "47569"
    },
    {
        "Friday": "09:00~18:00",
        "Monday": "09:00~18:00",
        "Saturday": "09:00~13:00",
        "Sunday": "~",
        "Thursday": "09:00~18:00",
        "Tuesday": "09:00~18:00",
        "Wednesday": "09:00~18:00",
        "exam_part": "가정의학과,내과,소아청소년과,이비인후과,피부과",
        "holiday": "~",
        "instit_kind": "의원",
        "instit_nm": "하은소아청소년과의원",
        "lat": "35.14785602",
        "lng": "129.0588986",
        "medical_instit_kind": "응급의료기관이외",
        "organ_loc": "1호선 범내골역 5,7번출구",
        "regist_dt": "2021-02-10",
        "street_nm_addr": "부산광역시 부산진구 중앙대로 617, 3층 (범천동)",
        "sunday_oper_week": "",
        "tel": "051-631-6003",
        "update_dt": "2021-02-10",
        "zip_code": "47351"
    },
    {
        "Friday": "09:30~19:00",
        "Monday": "09:30~21:00",
        "Saturday": "~",
        "Sunday": "~",
        "Thursday": "14:30~21:00",
        "Tuesday": "09:30~19:00",
        "Wednesday": "09:30~19:00",
        "exam_part": "구강내과,구강병리과,구강악안면방사선과,구강안면외과,소아치과,예방치과,치과교정과,치과보존과,치과보철과,치주과,통합치의학과",
        "holiday": "~",
        "instit_kind": "치과의원",
        "instit_nm": "고운플란트치과의원",
        "lat": "35.16242025",
        "lng": "129.0632696",
        "medical_instit_kind": "응급의료기관이외",
        "organ_loc": "1호선 부전역 6번출구",
        "regist_dt": "2021-02-03",
        "street_nm_addr": "부산광역시 부산진구 중앙대로 792, 진흥프라자 3 일부층 (전포동)",
        "sunday_oper_week": "",
        "tel": "051-791-0066",
        "update_dt": "2021-02-10",
        "zip_code": "47241"
    },
    {
        "Friday": "09:00~18:00",
        "Monday": "09:00~18:00",
        "Saturday": "09:00~13:00",
        "Sunday": "~",
        "Thursday": "09:00~18:00",
        "Tuesday": "09:00~18:00",
        "Wednesday": "09:00~18:00",
        "exam_part": "외과",
        "holiday": "~",
        "instit_kind": "의원",
        "instit_nm": "따뜻함의원",
        "lat": "35.10062321",
        "lng": "128.993991",
        "medical_instit_kind": "응급의료기관이외",
        "organ_loc": "1호선 괴정역 3번출구",
        "regist_dt": "2021-02-03",
        "street_nm_addr": "부산광역시 사하구 낙동대로 208, 3,4층 (괴정동)",
        "sunday_oper_week": "",
        "tel": "051-717-3800",
        "update_dt": "2021-02-03",
        "zip_code": "49338"
    },
    {
        "Friday": "09:00~17:30",
        "Monday": "09:00~17:30",
        "Saturday": "09:00~15:00",
        "Sunday": "~",
        "Thursday": "09:00~17:30",
        "Tuesday": "09:00~17:30",
        "Wednesday": "09:00~17:30",
        "exam_part": "",
        "holiday": "~",
        "instit_kind": "약국",
        "instit_nm": "행복약국",
        "lat": "35.17749393",
        "lng": "129.0485354",
        "medical_instit_kind": "응급의료기관이외",
        "organ_loc": "",
        "regist_dt": "2021-01-27",
        "street_nm_addr": "부산광역시 부산진구 새싹로 240-1, 1층 (초읍동)",
        "sunday_oper_week": "",
        "tel": "051-805-2032",
        "update_dt": "2021-02-15",
        "zip_code": "47127"
    },
    {
        "Friday": "09:00~19:00",
        "Monday": "09:00~19:00",
        "Saturday": "09:00~16:00",
        "Sunday": "~",
        "Thursday": "09:00~19:00",
        "Tuesday": "09:00~19:00",
        "Wednesday": "09:00~19:00",
        "exam_part": "",
        "holiday": "~",
        "instit_kind": "약국",
        "instit_nm": "새빛약국",
        "lat": "35.10062321",
        "lng": "128.993991",
        "medical_instit_kind": "응급의료기관이외",
        "organ_loc": "1호선 괴정역 5번출구",
        "regist_dt": "2021-01-27",
        "street_nm_addr": "부산광역시 사하구 낙동대로 208, 101호 (괴정동)",
        "sunday_oper_week": "",
        "tel": "051-208-7119",
        "update_dt": "2021-01-27",
        "zip_code": "49338"
    },
    {
        "Friday": "09:30~18:30",
        "Monday": "09:30~18:30",
        "Saturday": "09:30~13:00",
        "Sunday": "~",
        "Thursday": "09:30~18:30",
        "Tuesday": "09:30~18:30",
        "Wednesday": "09:30~13:00",
        "exam_part": "구강안면외과,소아치과,예방치과,치과교정과,치과보존과,치과보철과,치주과",
        "holiday": "~",
        "instit_kind": "치과의원",
        "instit_nm": "탑플랜치과의원",
        "lat": "35.26618318",
        "lng": "129.226425",
        "medical_instit_kind": "응급의료기관이외",
        "organ_loc": "동해선 일광역 2번출구",
        "regist_dt": "2021-01-27",
        "street_nm_addr": "부산광역시 기장군 일광면 해빛로 13, 6층 601,602호",
        "sunday_oper_week": "",
        "tel": "051-723-2275",
        "update_dt": "2021-01-27",
        "zip_code": "46048"
    },
    {
        "Friday": "09:00~18:00",
        "Monday": "09:00~18:00",
        "Saturday": "~",
        "Sunday": "~",
        "Thursday": "09:00~18:00",
        "Tuesday": "09:00~18:00",
        "Wednesday": "09:00~18:00",
        "exam_part": "구강내과,구강병리과,구강악안면방사선과,구강안면외과,소아치과,예방치과,치과교정과,치과보존과,치과보철과,치주과",
        "holiday": "~",
        "instit_kind": "치과의원",
        "instit_nm": "장치과의원",
        "lat": "35.31288542",
        "lng": "129.2446369",
        "medical_instit_kind": "응급의료기관이외",
        "organ_loc": "장안읍행정복지센터 인근",
        "regist_dt": "2021-01-27",
        "street_nm_addr": "부산광역시 기장군 장안읍 해맞이로 9, 2층 203호",
        "sunday_oper_week": "",
        "tel": "051-728-5522",
        "update_dt": "2021-02-15",
        "zip_code": "46033"
    },
    {
        "Friday": "09:00~21:00",
        "Monday": "09:00~21:00",
        "Saturday": "09:00~17:00",
        "Sunday": "~",
        "Thursday": "09:00~17:00",
        "Tuesday": "09:00~21:00",
        "Wednesday": "09:00~17:00",
        "exam_part": "사상체질과,침구과,한방내과,한방부인과,한방소아과,한방신경정신과,한방안이비인후피부과,한방재활의학과",
        "holiday": "~",
        "instit_kind": "한의원",
        "instit_nm": "호일침한의원",
        "lat": "35.15943167",
        "lng": "129.0556023",
        "medical_instit_kind": "응급의료기관이외",
        "organ_loc": "1,2호선 서면역 9번출구",
        "regist_dt": "2021-01-21",
        "street_nm_addr": "부산광역시 부산진구 서면문화로 27, 유원 골든타워 오피스텔 20층 (부전동)",
        "sunday_oper_week": "",
        "tel": "1577-1775",
        "update_dt": "2021-01-21",
        "zip_code": "47257"
    },
    {
        "Friday": "10:00~18:30",
        "Monday": "10:00~18:30",
        "Saturday": "10:00~15:00",
        "Sunday": "~",
        "Thursday": "10:00~18:30",
        "Tuesday": "10:00~18:30",
        "Wednesday": "10:00~18:30",
        "exam_part": "구강내과,구강병리과,구강악안면방사선과,구강안면외과,소아치과,예방치과,치과교정과,치과보존과,치과보철과,치주과",
        "holiday": "~",
        "instit_kind": "치과의원",
        "instit_nm": "박우경치과교정과치과의원",
        "lat": "35.16535756",
        "lng": "129.1144818",
        "medical_instit_kind": "응급의료기관이외",
        "organ_loc": "2,3호선 수영역 10번 출구 커피빈 5층",
        "regist_dt": "2021-01-21",
        "street_nm_addr": "부산광역시 수영구 수영로 667, 5층 (광안동)",
        "sunday_oper_week": "",
        "tel": "051-714-2636",
        "update_dt": "2021-01-21",
        "zip_code": "48243"
    },
    {
        "Friday": "09:30~18:30",
        "Monday": "09:30~18:30",
        "Saturday": "09:30~14:00",
        "Sunday": "~",
        "Thursday": "09:30~18:30",
        "Tuesday": "09:30~18:30",
        "Wednesday": "09:30~20:00",
        "exam_part": "구강내과,구강안면외과,소아치과,예방치과,치과교정과,치과보존과,치과보철과,치주과",
        "holiday": "~",
        "instit_kind": "치과의원",
        "instit_nm": "당감미치과의원",
        "lat": "35.16561787",
        "lng": "129.0386352",
        "medical_instit_kind": "응급의료기관이외",
        "organ_loc": "2호선 부암역 6번출구",
        "regist_dt": "2021-01-21",
        "street_nm_addr": "부산광역시 부산진구 동평로 83, 미래메디칼 5층 (당감동)",
        "sunday_oper_week": "",
        "tel": "051-898-2888",
        "update_dt": "2021-01-21",
        "zip_code": "47145"
    },
    {
        "Friday": "09:00~18:00",
        "Monday": "09:00~18:00",
        "Saturday": "09:00~13:00",
        "Sunday": "~",
        "Thursday": "09:00~18:00",
        "Tuesday": "09:00~18:00",
        "Wednesday": "09:00~18:00",
        "exam_part": "마취통증의학과,신경외과,정형외과",
        "holiday": "~",
        "instit_kind": "의원",
        "instit_nm": "시원마취통증의학과의원",
        "lat": "35.15881919",
        "lng": "129.0576139",
        "medical_instit_kind": "응급의료기관이외",
        "organ_loc": "",
        "regist_dt": "2021-01-21",
        "street_nm_addr": "부산광역시 부산진구 서면문화로 10, 17층 (부전동)",
        "sunday_oper_week": "",
        "tel": "051-802-7541",
        "update_dt": "2021-01-21",
        "zip_code": "47256"
    },
    {
        "Friday": "09:30~18:30",
        "Monday": "09:30~18:30",
        "Saturday": "09:30~15:30",
        "Sunday": "~",
        "Thursday": "09:30~18:30",
        "Tuesday": "09:30~18:30",
        "Wednesday": "09:30~18:30",
        "exam_part": "안과",
        "holiday": "~",
        "instit_kind": "의원",
        "instit_nm": "부산글로벌서울안과의원",
        "lat": "35.15294507",
        "lng": "129.0572744",
        "medical_instit_kind": "응급의료기관이외",
        "organ_loc": "1,2호선 서면역 7번출구",
        "regist_dt": "2021-01-21",
        "street_nm_addr": "부산광역시 부산진구 서면로 25, 4층 (부전동)",
        "sunday_oper_week": "",
        "tel": "051-951-2020",
        "update_dt": "2021-01-21",
        "zip_code": "47288"
    },
    {
        "Friday": "09:00~17:00",
        "Monday": "09:00~17:00",
        "Saturday": "09:00~14:00",
        "Sunday": "~",
        "Thursday": "09:00~17:00",
        "Tuesday": "09:00~17:00",
        "Wednesday": "09:00~17:00",
        "exam_part": "가정의학과,내과,신경외과",
        "holiday": "~",
        "instit_kind": "의원",
        "instit_nm": "김진목파인힐의원",
        "lat": "35.17376574",
        "lng": "129.1811665",
        "medical_instit_kind": "응급의료기관이외",
        "organ_loc": "2호선 장산역 2번출구",
        "regist_dt": "2021-01-21",
        "street_nm_addr": "부산광역시 해운대구 좌동순환로 247, 유안빌딩 4,5층 (좌동)",
        "sunday_oper_week": "",
        "tel": "051-710-0005",
        "update_dt": "2021-01-21",
        "zip_code": "48108"
    },
    {
        "Friday": "09:00~18:00",
        "Monday": "09:00~18:00",
        "Saturday": "09:00~14:00",
        "Sunday": "~",
        "Thursday": "09:00~18:00",
        "Tuesday": "09:00~18:00",
        "Wednesday": "09:00~18:00",
        "exam_part": "외과",
        "holiday": "~",
        "instit_kind": "의원",
        "instit_nm": "위드맘유갑외과의원",
        "lat": "35.10586979",
        "lng": "128.9638463",
        "medical_instit_kind": "응급의료기관이외",
        "organ_loc": "1호선 하단역 2번출구",
        "regist_dt": "2021-01-15",
        "street_nm_addr": "부산광역시 사하구 낙동남로 1392, 2,6층 (하단동)",
        "sunday_oper_week": "",
        "tel": "051-204-3500",
        "update_dt": "2021-01-29",
        "zip_code": "49426"
    },
    {
        "Friday": "08:00~17:00",
        "Monday": "08:00~17:00",
        "Saturday": "08:00~13:00",
        "Sunday": "~",
        "Thursday": "08:00~17:00",
        "Tuesday": "08:00~17:00",
        "Wednesday": "08:00~17:00",
        "exam_part": "외과",
        "holiday": "~",
        "instit_kind": "의원",
        "instit_nm": "도담외과의원",
        "lat": "35.15987335",
        "lng": "129.0577033",
        "medical_instit_kind": "응급의료기관이외",
        "organ_loc": "1,2호선 서면역 13번 출구",
        "regist_dt": "2021-01-14",
        "street_nm_addr": "부산광역시 부산진구 새싹로 22-1, 2층 (부전동)",
        "sunday_oper_week": "",
        "tel": "051-711-6119",
        "update_dt": "2021-02-15",
        "zip_code": "47253"
    },
    {
        "Friday": "09:00~19:00",
        "Monday": "09:00~19:00",
        "Saturday": "09:00~14:00",
        "Sunday": "~",
        "Thursday": "09:00~19:00",
        "Tuesday": "09:00~19:00",
        "Wednesday": "09:00~14:00",
        "exam_part": "사상체질과,침구과,한방내과,한방부인과,한방소아과,한방신경정신과,한방안이비인후피부과,한방재활의학과",
        "holiday": "~",
        "instit_kind": "한의원",
        "instit_nm": "해담한의원",
        "lat": "35.1681342",
        "lng": "129.1163968",
        "medical_instit_kind": "응급의료기관이외",
        "organ_loc": "수영역 3번 출구",
        "regist_dt": "2021-01-12",
        "street_nm_addr": "부산광역시 수영구 수영로705번길 5, 엠에스빌딩 2층 (수영동)",
        "sunday_oper_week": "",
        "tel": "051-755-0707",
        "update_dt": "2021-01-21",
        "zip_code": "48228"
    },
    {
        "Friday": "10:00~19:30",
        "Monday": "10:00~19:30",
        "Saturday": "09:00~15:00",
        "Sunday": "~",
        "Thursday": "10:00~19:30",
        "Tuesday": "10:00~19:30",
        "Wednesday": "10:00~19:30",
        "exam_part": "사상체질과,침구과,한방내과,한방부인과,한방소아과,한방신경정신과,한방안이비인후피부과,한방재활의학과",
        "holiday": "~",
        "instit_kind": "한의원",
        "instit_nm": "정관에스(S)한의원",
        "lat": "35.32062942",
        "lng": "129.1770764",
        "medical_instit_kind": "응급의료기관이외",
        "organ_loc": "버스정류장 : 정관농협기업지점",
        "regist_dt": "2021-01-12",
        "street_nm_addr": "부산광역시 기장군 정관읍 정관로 580, 2층 202-204호",
        "sunday_oper_week": "",
        "tel": "051-723-9500",
        "update_dt": "2021-01-12",
        "zip_code": "46017"
    },
    {
        "Friday": "09:00~19:30",
        "Monday": "09:00~19:30",
        "Saturday": "09:00~15:00",
        "Sunday": "09:00~13:00",
        "Thursday": "09:00~19:30",
        "Tuesday": "09:00~19:30",
        "Wednesday": "09:00~19:30",
        "exam_part": "",
        "holiday": "09:00~13:00",
        "instit_kind": "약국",
        "instit_nm": "하늘약국",
        "lat": "35.13888827",
        "lng": "129.1071195",
        "medical_instit_kind": "응급의료기관이외",
        "organ_loc": "",
        "regist_dt": "2021-01-12",
        "street_nm_addr": "부산광역시 수영구 황령대로 483, 한나빌딩 (남천동)",
        "sunday_oper_week": "1 2 3 4 5",
        "tel": "051-626-7200",
        "update_dt": "2021-02-08",
        "zip_code": "48312"
    },
    {
        "Friday": "08:30~19:30",
        "Monday": "08:30~19:30",
        "Saturday": "08:30~14:00",
        "Sunday": "~",
        "Thursday": "08:30~19:30",
        "Tuesday": "08:30~19:30",
        "Wednesday": "08:30~19:30",
        "exam_part": "",
        "holiday": "~",
        "instit_kind": "약국",
        "instit_nm": "새중앙약국",
        "lat": "35.21442528",
        "lng": "129.0347651",
        "medical_instit_kind": "응급의료기관이외",
        "organ_loc": "3호선 만덕역 4번 출구",
        "regist_dt": "2021-01-12",
        "street_nm_addr": "부산광역시 북구 만덕1로 26, 중앙빌딩 101호 (만덕동)",
        "sunday_oper_week": "",
        "tel": "051-932-8532",
        "update_dt": "2021-01-12",
        "zip_code": "46557"
    },
    {
        "Friday": "10:00~19:00",
        "Monday": "10:00~19:00",
        "Saturday": "10:00~13:00",
        "Sunday": "~",
        "Thursday": "10:00~19:00",
        "Tuesday": "10:00~19:00",
        "Wednesday": "10:00~19:30",
        "exam_part": "치과",
        "holiday": "~",
        "instit_kind": "치과의원",
        "instit_nm": "율리프라임치과의원",
        "lat": "35.24697707",
        "lng": "129.0131594",
        "medical_instit_kind": "응급의료기관이외",
        "organ_loc": "2호선 율리역 4번 출구",
        "regist_dt": "2021-01-12",
        "street_nm_addr": "부산광역시 북구 금곡대로 432, 3층 (금곡동)",
        "sunday_oper_week": "",
        "tel": "051-362-2275",
        "update_dt": "2021-01-12",
        "zip_code": "46511"
    },
    {
        "Friday": "09:00~18:00",
        "Monday": "~",
        "Saturday": "09:00~17:00",
        "Sunday": "~",
        "Thursday": "09:00~18:00",
        "Tuesday": "09:00~18:00",
        "Wednesday": "09:00~18:00",
        "exam_part": "내과,소아청소년과,이비인후과",
        "holiday": "~",
        "instit_kind": "의원",
        "instit_nm": "최원복소아청소년과의원",
        "lat": "35.1382223",
        "lng": "129.1010753",
        "medical_instit_kind": "응급의료기관이외",
        "organ_loc": "2호선 경성대부경대역 2번출구",
        "regist_dt": "2021-01-12",
        "street_nm_addr": "부산광역시 남구 수영로 323, 태강프라자 201호 (대연동)",
        "sunday_oper_week": "",
        "tel": "051-628-7711",
        "update_dt": "2021-01-12",
        "zip_code": "48434"
    },
    {
        "Friday": "09:00~18:30",
        "Monday": "09:00~18:30",
        "Saturday": "09:00~13:00",
        "Sunday": "~",
        "Thursday": "09:00~18:30",
        "Tuesday": "09:00~18:30",
        "Wednesday": "09:00~18:30",
        "exam_part": "내과,마취통증의학과,신경외과,영상의학과,외과,재활의학과,정형외과,피부과",
        "holiday": "~",
        "instit_kind": "의원",
        "instit_nm": "조은어깨동무정형외과의원",
        "lat": "35.22233171",
        "lng": "129.084999",
        "medical_instit_kind": "응급의료기관이외",
        "organ_loc": "온천장역 5번출구, 홈플러스 뒷편",
        "regist_dt": "2021-01-12",
        "street_nm_addr": "부산광역시 금정구 온천장로 131 (장전동)",
        "sunday_oper_week": "",
        "tel": "051-711-5365",
        "update_dt": "2021-01-27",
        "zip_code": "46300"
    },
    {
        "Friday": "14:00~21:00",
        "Monday": "14:00~21:00",
        "Saturday": "10:00~16:00",
        "Sunday": "~",
        "Thursday": "11:00~19:00",
        "Tuesday": "11:00~19:00",
        "Wednesday": "14:00~21:00",
        "exam_part": "피부과",
        "holiday": "~",
        "instit_kind": "의원",
        "instit_nm": "리쥬브포맨의원",
        "lat": "35.15937507",
        "lng": "129.0600139",
        "medical_instit_kind": "응급의료기관이외",
        "organ_loc": "1호선 서면역 15번 출구",
        "regist_dt": "2021-01-12",
        "street_nm_addr": "부산광역시 부산진구 중앙대로 747, 2층 (부전동)",
        "sunday_oper_week": "",
        "tel": "051-808-0008",
        "update_dt": "2021-01-12",
        "zip_code": "47254"
    },
    {
        "Friday": "09:30~18:30",
        "Monday": "09:30~18:30",
        "Saturday": "09:30~14:00",
        "Sunday": "~",
        "Thursday": "09:30~18:30",
        "Tuesday": "09:30~18:30",
        "Wednesday": "14:00~21:00",
        "exam_part": "구강내과,구강병리과,구강악안면방사선과,구강안면외과,소아치과,예방치과,치과교정과,치과보존과,치과보철과,치주과,통합치의학과",
        "holiday": "~",
        "instit_kind": "치과의원",
        "instit_nm": "이센스치과의원",
        "lat": "35.20092691",
        "lng": "129.0866686",
        "medical_instit_kind": "응급의료기관이외",
        "organ_loc": "수안역 8번출구",
        "regist_dt": "2021-01-06",
        "street_nm_addr": "부산광역시 동래구 충렬대로 252, 4층 (수안동)",
        "sunday_oper_week": "",
        "tel": "051-557-2828",
        "update_dt": "2021-01-06",
        "zip_code": "47877"
    },
    {
        "Friday": "~",
        "Monday": "~",
        "Saturday": "~",
        "Sunday": "~",
        "Thursday": "~",
        "Tuesday": "~",
        "Wednesday": "~",
        "exam_part": "사상체질과,침구과,한방내과,한방부인과,한방소아과,한방신경정신과,한방안이비인후피부과,한방재활의학과",
        "holiday": "~",
        "instit_kind": "한의원",
        "instit_nm": "수+한의원",
        "lat": "35.07660279",
        "lng": "128.9726353",
        "medical_instit_kind": "응급의료기관이외",
        "organ_loc": "신장림역 3번출구",
        "regist_dt": "2021-01-04",
        "street_nm_addr": "부산광역시 사하구 장평로 117, 서진빌딩 201호 (장림동)",
        "sunday_oper_week": "",
        "tel": "051-923-5853",
        "update_dt": "2021-01-27",
        "zip_code": "49483"
    },
    {
        "Friday": "12:00~21:00",
        "Monday": "12:00~21:00",
        "Saturday": "10:00~16:00",
        "Sunday": "~",
        "Thursday": "12:00~21:00",
        "Tuesday": "12:00~21:00",
        "Wednesday": "12:00~21:00",
        "exam_part": "사상체질과,침구과,한방내과,한방부인과,한방소아과,한방신경정신과,한방안이비인후피부과,한방재활의학과",
        "holiday": "~",
        "instit_kind": "한의원",
        "instit_nm": "하늘체한의원",
        "lat": "35.18622725",
        "lng": "129.0824321",
        "medical_instit_kind": "응급의료기관이외",
        "organ_loc": "1호선 연산역 10, 12번 출구",
        "regist_dt": "2020-12-29",
        "street_nm_addr": "부산광역시 연제구 반송로 6, 6층 (연산동)",
        "sunday_oper_week": "",
        "tel": "051-868-7866",
        "update_dt": "2021-02-08",
        "zip_code": "47549"
    },
    {
        "Friday": "09:00~19:00",
        "Monday": "09:00~19:00",
        "Saturday": "09:00~13:00",
        "Sunday": "~",
        "Thursday": "09:00~19:00",
        "Tuesday": "09:00~19:00",
        "Wednesday": "09:00~19:00",
        "exam_part": "",
        "holiday": "~",
        "instit_kind": "약국",
        "instit_nm": "보담약국",
        "lat": "35.14599148",
        "lng": "129.0597743",
        "medical_instit_kind": "응급의료기관이외",
        "organ_loc": "1호선 범내골역 2번 출구",
        "regist_dt": "2020-12-29",
        "street_nm_addr": "부산광역시 부산진구 범일로 178, 1층 (범천동)",
        "sunday_oper_week": "",
        "tel": "051-990-9000",
        "update_dt": "2020-12-29",
        "zip_code": "47357"
    },
    {
        "Friday": "09:00~19:00",
        "Monday": "09:00~19:00",
        "Saturday": "09:00~15:00",
        "Sunday": "09:00~15:00",
        "Thursday": "09:00~19:00",
        "Tuesday": "09:00~19:00",
        "Wednesday": "09:00~19:00",
        "exam_part": "가정의학과,내과,비뇨의학과,소아청소년과,안과,이비인후과,정형외과,피부과",
        "holiday": "09:00~15:00",
        "instit_kind": "의원",
        "instit_nm": "더큰아이소아청소년과의원",
        "lat": "35.16879795",
        "lng": "129.1757377",
        "medical_instit_kind": "응급의료기관이외",
        "organ_loc": "2호선 장산역 11, 13번 출구",
        "regist_dt": "2020-12-29",
        "street_nm_addr": "부산광역시 해운대구 해운대로 794, 엘리움 201~203호 (좌동)",
        "sunday_oper_week": "1 2 3 4 5",
        "tel": "051-711-7878",
        "update_dt": "2020-12-29",
        "zip_code": "48104"
    },
    {
        "Friday": "08:00~21:00",
        "Monday": "08:00~21:00",
        "Saturday": "08:00~18:00",
        "Sunday": "08:00~18:00",
        "Thursday": "08:00~21:00",
        "Tuesday": "08:00~21:00",
        "Wednesday": "08:00~21:00",
        "exam_part": "내과,소아청소년과,신경외과,정형외과,피부과",
        "holiday": "09:00~21:00",
        "instit_kind": "의원",
        "instit_nm": "다대의원",
        "lat": "35.06129627",
        "lng": "128.9760603",
        "medical_instit_kind": "응급의료기관이외",
        "organ_loc": "버스정류장 : 다대현대아파트",
        "regist_dt": "2020-12-29",
        "street_nm_addr": "부산광역시 사하구 다대로 485, 일영빌딩 B동 3층 (다대동)",
        "sunday_oper_week": "1 3 5",
        "tel": "051-912-3636",
        "update_dt": "2020-12-29",
        "zip_code": "49520"
    },
    {
        "Friday": "10:00~19:00",
        "Monday": "10:00~19:00",
        "Saturday": "10:00~14:00",
        "Sunday": "~",
        "Thursday": "10:00~20:00",
        "Tuesday": "10:00~19:00",
        "Wednesday": "10:00~19:00",
        "exam_part": "구강내과,구강안면외과,소아치과,예방치과,치과교정과,치과보존과,치과보철과,치주과,통합치의학과",
        "holiday": "~",
        "instit_kind": "치과의원",
        "instit_nm": "남천바른생각치과의원",
        "lat": "35.14180721",
        "lng": "129.1072908",
        "medical_instit_kind": "응급의료기관이외",
        "organ_loc": "2호선 남천역 4번출구",
        "regist_dt": "2020-12-28",
        "street_nm_addr": "부산광역시 수영구 수영로 393, 예진메디칼센타 3층 (남천동)",
        "sunday_oper_week": "",
        "tel": "051-623-2875",
        "update_dt": "2021-01-14",
        "zip_code": "48317"
    },
    {
        "Friday": "09:00~18:30",
        "Monday": "09:00~18:30",
        "Saturday": "09:00~13:30",
        "Sunday": "~",
        "Thursday": "09:00~18:30",
        "Tuesday": "09:00~18:30",
        "Wednesday": "09:00~18:30",
        "exam_part": "",
        "holiday": "~",
        "instit_kind": "약국",
        "instit_nm": "편한약국",
        "lat": "35.26093307",
        "lng": "129.0885251",
        "medical_instit_kind": "응급의료기관이외",
        "organ_loc": "버스정류장 : 샘골공원",
        "regist_dt": "2020-12-23",
        "street_nm_addr": "부산광역시 금정구 두실로 26, 진경빌딩 1층 (남산동)",
        "sunday_oper_week": "",
        "tel": "051-583-8123",
        "update_dt": "2020-12-23",
        "zip_code": "46227"
    },
    {
        "Friday": "09:30~18:30",
        "Monday": "09:30~18:30",
        "Saturday": "09:30~13:30",
        "Sunday": "~",
        "Thursday": "09:30~18:30",
        "Tuesday": "09:30~18:30",
        "Wednesday": "09:30~18:30",
        "exam_part": "산부인과",
        "holiday": "~",
        "instit_kind": "의원",
        "instit_nm": "루이송여성의원",
        "lat": "35.15806536",
        "lng": "129.057231",
        "medical_instit_kind": "응급의료기관이외",
        "organ_loc": "2호선 서면역 9번 출구",
        "regist_dt": "2020-12-22",
        "street_nm_addr": "부산광역시 부산진구 가야대로 783, 4층 (부전동)",
        "sunday_oper_week": "",
        "tel": "051-806-9993",
        "update_dt": "2020-12-22",
        "zip_code": "47257"
    },
    {
        "Friday": "09:00~19:00",
        "Monday": "09:00~19:00",
        "Saturday": "09:00~13:00",
        "Sunday": "~",
        "Thursday": "09:00~19:00",
        "Tuesday": "09:00~19:00",
        "Wednesday": "09:00~19:00",
        "exam_part": "",
        "holiday": "~",
        "instit_kind": "약국",
        "instit_nm": "파랑약국",
        "lat": "35.20210531",
        "lng": "129.1195417",
        "medical_instit_kind": "응급의료기관이외",
        "organ_loc": "",
        "regist_dt": "2020-12-16",
        "street_nm_addr": "부산광역시 해운대구 선수촌로 94, 대룡빌딩 102호 (반여동)",
        "sunday_oper_week": "",
        "tel": "051-526-8900",
        "update_dt": "2020-12-16",
        "zip_code": "48037"
    },
    {
        "Friday": "09:30~18:00",
        "Monday": "09:30~18:00",
        "Saturday": "09:30~13:00",
        "Sunday": "~",
        "Thursday": "09:30~18:00",
        "Tuesday": "09:30~18:00",
        "Wednesday": "09:30~18:00",
        "exam_part": "내과,산부인과,외과,이비인후과,작업환경의학과,정형외과,피부과",
        "holiday": "~",
        "instit_kind": "의원",
        "instit_nm": "휴암의원",
        "lat": "35.17196043",
        "lng": "129.174949",
        "medical_instit_kind": "응급의료기관이외",
        "organ_loc": "",
        "regist_dt": "2020-12-16",
        "street_nm_addr": "부산광역시 해운대구 좌동로 88, 울트라타워 1301~1302호 (좌동)",
        "sunday_oper_week": "",
        "tel": "051-704-7779",
        "update_dt": "2021-02-03",
        "zip_code": "48106"
    },
    {
        "Friday": "09:30~18:30",
        "Monday": "09:30~18:30",
        "Saturday": "09:30~13:30",
        "Sunday": "~",
        "Thursday": "09:30~13:30",
        "Tuesday": "09:30~18:30",
        "Wednesday": "09:30~18:30",
        "exam_part": "내과,신경과,정신건강의학과",
        "holiday": "~",
        "instit_kind": "의원",
        "instit_nm": "인성정신건강의학과의원",
        "lat": "35.14091615",
        "lng": "129.107147",
        "medical_instit_kind": "응급의료기관이외",
        "organ_loc": "",
        "regist_dt": "2020-12-16",
        "street_nm_addr": "부산광역시 수영구 수영로 386-1, 원탄크리닉 601호 (남천동)",
        "sunday_oper_week": "",
        "tel": "051-626-3331",
        "update_dt": "2020-12-16",
        "zip_code": "48311"
    },
    {
        "Friday": "09:00~18:00",
        "Monday": "09:00~18:00",
        "Saturday": "09:00~13:00",
        "Sunday": "~",
        "Thursday": "09:00~18:00",
        "Tuesday": "09:00~18:00",
        "Wednesday": "09:00~18:00",
        "exam_part": "내과,마취통증의학과,신경외과,재활의학과,정형외과",
        "holiday": "~",
        "instit_kind": "의원",
        "instit_nm": "수안의원",
        "lat": "35.20266866",
        "lng": "129.0814095",
        "medical_instit_kind": "응급의료기관이외",
        "organ_loc": "수안역 2번 출구",
        "regist_dt": "2020-12-16",
        "street_nm_addr": "부산광역시 동래구 충렬대로 200, 불이빌딩 11층 (수안동)",
        "sunday_oper_week": "",
        "tel": "051-556-7979",
        "update_dt": "2021-02-10",
        "zip_code": "47816"
    },
    {
        "Friday": "10:00~21:00",
        "Monday": "10:00~19:00",
        "Saturday": "10:00~13:00",
        "Sunday": "~",
        "Thursday": "10:00~19:00",
        "Tuesday": "10:00~19:00",
        "Wednesday": "10:00~13:00",
        "exam_part": "내과,마취통증의학과,성형외과,신경외과,정형외과,피부과",
        "holiday": "~",
        "instit_kind": "의원",
        "instit_nm": "동백제니스의원",
        "lat": "35.15972737",
        "lng": "129.1507025",
        "medical_instit_kind": "응급의료기관이외",
        "organ_loc": "2호선 동백역 1,2번 출구(두산위브더제니스아파트)",
        "regist_dt": "2020-12-16",
        "street_nm_addr": "부산광역시 해운대구 해운대로 540, 105~109호 (우동, 해운대 동백 두산위브더제니스)",
        "sunday_oper_week": "",
        "tel": "051-747-3490",
        "update_dt": "2021-01-12",
        "zip_code": "48093"
    },
    {
        "Friday": "09:00~17:00",
        "Monday": "09:00~17:30",
        "Saturday": "09:00~12:00",
        "Sunday": "~",
        "Thursday": "09:00~17:30",
        "Tuesday": "09:00~17:30",
        "Wednesday": "09:00~17:30",
        "exam_part": "내과,성형외과,신경과,외과,이비인후과,피부과",
        "holiday": "~",
        "instit_kind": "병원",
        "instit_nm": "의료법인서호의료재단 서호하단병원",
        "lat": "35.10523399",
        "lng": "128.970091",
        "medical_instit_kind": "응급의료기관이외",
        "organ_loc": "",
        "regist_dt": "2020-12-16",
        "street_nm_addr": "부산광역시 사하구 낙동대로 446, 7-14층 (당리동)",
        "sunday_oper_week": "",
        "tel": "051-201-6666",
        "update_dt": "2021-01-22",
        "zip_code": "49326"
    },
    {
        "Friday": "09:30~19:00",
        "Monday": "09:30~19:00",
        "Saturday": "09:30~13:00",
        "Sunday": "~",
        "Thursday": "09:30~19:00",
        "Tuesday": "09:30~19:00",
        "Wednesday": "09:30~19:00",
        "exam_part": "",
        "holiday": "~",
        "instit_kind": "약국",
        "instit_nm": "행복온누리약국",
        "lat": "35.22418399",
        "lng": "129.0084927",
        "medical_instit_kind": "응급의료기관이외",
        "organ_loc": "2호선 수정역 3번출구",
        "regist_dt": "2020-12-07",
        "street_nm_addr": "부산광역시 북구 학사로 8, 크리스탈타워 1층 102호 (화명동)",
        "sunday_oper_week": "",
        "tel": "051-365-4577",
        "update_dt": "2020-12-07",
        "zip_code": "46541"
    },
    {
        "Friday": "09:00~21:00",
        "Monday": "09:00~21:00",
        "Saturday": "09:00~21:00",
        "Sunday": "~",
        "Thursday": "09:00~21:00",
        "Tuesday": "09:00~21:00",
        "Wednesday": "09:00~21:00",
        "exam_part": "",
        "holiday": "~",
        "instit_kind": "약국",
        "instit_nm": "수경메디컬약국",
        "lat": "35.06129627",
        "lng": "128.9760603",
        "medical_instit_kind": "응급의료기관이외",
        "organ_loc": "",
        "regist_dt": "2020-12-07",
        "street_nm_addr": "부산광역시 사하구 다대로 485, 일영빌딩 B동 201호 (다대동)",
        "sunday_oper_week": "",
        "tel": "051-914-9965",
        "update_dt": "2021-01-14",
        "zip_code": "49520"
    },
    {
        "Friday": "09:30~18:30",
        "Monday": "09:30~18:30",
        "Saturday": "09:30~14:00",
        "Sunday": "~",
        "Thursday": "09:30~20:00",
        "Tuesday": "09:30~18:30",
        "Wednesday": "09:30~18:30",
        "exam_part": "내과,외과,피부과",
        "holiday": "~",
        "instit_kind": "의원",
        "instit_nm": "미담유외과의원",
        "lat": "35.16591625",
        "lng": "129.1145004",
        "medical_instit_kind": "응급의료기관이외",
        "organ_loc": "2호선 수영역8번 출구",
        "regist_dt": "2020-12-07",
        "street_nm_addr": "부산광역시 수영구 수영로 675, 큐비 메디컬센터 11층 (광안동)",
        "sunday_oper_week": "",
        "tel": "051-754-6660",
        "update_dt": "2021-01-11",
        "zip_code": "48243"
    },
    {
        "Friday": "~",
        "Monday": "10:00~18:30",
        "Saturday": "10:00~14:30",
        "Sunday": "10:00~14:30",
        "Thursday": "10:00~18:30",
        "Tuesday": "10:00~18:30",
        "Wednesday": "10:00~18:30",
        "exam_part": "구강내과,구강병리과,구강악안면방사선과,구강안면외과,소아치과,예방치과,치과교정과,치과보존과,치과보철과,치주과",
        "holiday": "10:00~18:30",
        "instit_kind": "치과의원",
        "instit_nm": "아시아드치과의원",
        "lat": "35.1962919",
        "lng": "129.0676536",
        "medical_instit_kind": "응급의료기관이외",
        "organ_loc": "3호선 사직역 2번출구",
        "regist_dt": "2020-12-01",
        "street_nm_addr": "부산광역시 동래구 아시아드대로134번길 14, 상가1동 2층 201,202,203호 (사직동, 쌍용더플래티넘사직아시아드아파트)",
        "sunday_oper_week": "1 2 3 4 5",
        "tel": "051-503-7070",
        "update_dt": "2020-12-01",
        "zip_code": "47844"
    },
    {
        "Friday": "09:30~18:00",
        "Monday": "09:30~18:00",
        "Saturday": "09:30~13:00",
        "Sunday": "~",
        "Thursday": "09:30~18:00",
        "Tuesday": "09:30~18:00",
        "Wednesday": "09:30~18:00",
        "exam_part": "비뇨의학과,피부과",
        "holiday": "~",
        "instit_kind": "의원",
        "instit_nm": "홍진욱비뇨의학과의원",
        "lat": "35.16879795",
        "lng": "129.1757377",
        "medical_instit_kind": "응급의료기관이외",
        "organ_loc": "2호선 장산역 13번 출구",
        "regist_dt": "2020-12-01",
        "street_nm_addr": "부산광역시 해운대구 해운대로 794, 엘리움 301호, 302일부호 (좌동)",
        "sunday_oper_week": "",
        "tel": "051-742-7575",
        "update_dt": "2020-12-21",
        "zip_code": "48104"
    },
    {
        "Friday": "09:00~18:00",
        "Monday": "09:00~18:00",
        "Saturday": "09:00~13:00",
        "Sunday": "~",
        "Thursday": "09:00~20:00",
        "Tuesday": "09:00~20:00",
        "Wednesday": "09:00~18:00",
        "exam_part": "내과,마취통증의학과,소아청소년과,신경과,신경외과,영상의학과,외과,응급의학과,재활의학과,정형외과,피부과,흉부외과",
        "holiday": "~",
        "instit_kind": "의원",
        "instit_nm": "올바른신경외과의원",
        "lat": "35.13458415",
        "lng": "129.0867288",
        "medical_instit_kind": "응급의료기관이외",
        "organ_loc": "2호선 못골역 1번 출구",
        "regist_dt": "2020-12-01",
        "street_nm_addr": "부산광역시 남구 수영로 184, 4층 (대연동)",
        "sunday_oper_week": "",
        "tel": "051-715-8212",
        "update_dt": "2020-12-28",
        "zip_code": "48460"
    },
    {
        "Friday": "09:30~18:30",
        "Monday": "09:30~18:30",
        "Saturday": "09:30~14:00",
        "Sunday": "~",
        "Thursday": "09:30~18:30",
        "Tuesday": "09:30~18:30",
        "Wednesday": "09:30~20:00",
        "exam_part": "신경과,정신건강의학과",
        "holiday": "~",
        "instit_kind": "의원",
        "instit_nm": "마음인정신건강의학과의원",
        "lat": "35.15584328",
        "lng": "129.0587937",
        "medical_instit_kind": "응급의료기관이외",
        "organ_loc": "1호선 서면역 1번 출구",
        "regist_dt": "2020-12-01",
        "street_nm_addr": "부산광역시 부산진구 중앙대로 707, 10층 (부전동)",
        "sunday_oper_week": "",
        "tel": "051-817-0032",
        "update_dt": "2020-12-01",
        "zip_code": "47286"
    },
    {
        "Friday": "09:00~20:00",
        "Monday": "09:00~20:00",
        "Saturday": "09:00~17:00",
        "Sunday": "~",
        "Thursday": "09:00~20:00",
        "Tuesday": "09:00~20:00",
        "Wednesday": "09:00~20:00",
        "exam_part": "",
        "holiday": "09:00~14:00",
        "instit_kind": "약국",
        "instit_nm": "진약국",
        "lat": "35.09128269",
        "lng": "128.9033555",
        "medical_instit_kind": "응급의료기관이외",
        "organ_loc": "",
        "regist_dt": "2020-11-30",
        "street_nm_addr": "부산광역시 강서구 명지국제1로 25, 우진메디컬프라 112호 (명지동)",
        "sunday_oper_week": "",
        "tel": "051-201-5481",
        "update_dt": "2020-11-30",
        "zip_code": "46726"
    },
    {
        "Friday": "09:30~20:00",
        "Monday": "09:30~18:00",
        "Saturday": "09:30~13:30",
        "Sunday": "~",
        "Thursday": "09:30~18:00",
        "Tuesday": "09:30~18:00",
        "Wednesday": "09:30~20:00",
        "exam_part": "산부인과",
        "holiday": "~",
        "instit_kind": "의원",
        "instit_nm": "지혜산부인과의원",
        "lat": "35.17285645",
        "lng": "129.07064",
        "medical_instit_kind": "응급의료기관이외",
        "organ_loc": "1호선 양정역 3번출구",
        "regist_dt": "2020-11-24",
        "street_nm_addr": "부산광역시 부산진구 동평로 422, 4층 (양정동)",
        "sunday_oper_week": "",
        "tel": "051-710-7722",
        "update_dt": "2020-11-24",
        "zip_code": "47213"
    },
    {
        "Friday": "09:30~20:00",
        "Monday": "09:30~20:00",
        "Saturday": "09:30~14:00",
        "Sunday": "~",
        "Thursday": "09:30~20:00",
        "Tuesday": "09:30~20:00",
        "Wednesday": "13:00~20:00",
        "exam_part": "가정의학과,내과,성형외과,소아청소년과,피부과",
        "holiday": "~",
        "instit_kind": "의원",
        "instit_nm": "맑고고운의원",
        "lat": "35.11371926",
        "lng": "129.1112871",
        "medical_instit_kind": "응급의료기관이외",
        "organ_loc": "",
        "regist_dt": "2020-11-23",
        "street_nm_addr": "부산광역시 남구 용호로 207, 7층 (용호동)",
        "sunday_oper_week": "",
        "tel": "051-628-7277",
        "update_dt": "2020-11-23",
        "zip_code": "48591"
    },
    {
        "Friday": "09:00~18:00",
        "Monday": "09:00~18:00",
        "Saturday": "09:00~13:00",
        "Sunday": "~",
        "Thursday": "09:00~18:00",
        "Tuesday": "09:00~18:00",
        "Wednesday": "09:00~18:00",
        "exam_part": "가정의학과,내과,마취통증의학과,비뇨의학과,산부인과,성형외과,외과,이비인후과,정신건강의학과,정형외과,피부과",
        "holiday": "~",
        "instit_kind": "의원",
        "instit_nm": "동래미래로여성의원",
        "lat": "35.20578993",
        "lng": "129.077091",
        "medical_instit_kind": "응급의료기관이외",
        "organ_loc": "4호선 동래역 5번출구",
        "regist_dt": "2020-11-23",
        "street_nm_addr": "부산광역시 동래구 충렬대로155번길 19, 3층 301호 (온천동)",
        "sunday_oper_week": "",
        "tel": "051-556-1331",
        "update_dt": "2020-11-23",
        "zip_code": "47734"
    },
    {
        "Friday": "09:30~20:00",
        "Monday": "09:30~20:00",
        "Saturday": "09:30~13:30",
        "Sunday": "~",
        "Thursday": "09:30~20:00",
        "Tuesday": "09:30~20:00",
        "Wednesday": "09:30~13:30",
        "exam_part": "내과,마취통증의학과,신경과,신경외과,재활의학과,정형외과",
        "holiday": "~",
        "instit_kind": "의원",
        "instit_nm": "광안리재활의학과의원",
        "lat": "35.15733346",
        "lng": "129.1127149",
        "medical_instit_kind": "응급의료기관이외",
        "organ_loc": "2호선 광안력 6번출구",
        "regist_dt": "2020-11-23",
        "street_nm_addr": "부산광역시 수영구 수영로 577, 9층 (광안동)",
        "sunday_oper_week": "",
        "tel": "051-757-7341",
        "update_dt": "2020-12-30",
        "zip_code": "48255"
    },
    {
        "Friday": "11:00~20:00",
        "Monday": "11:00~20:00",
        "Saturday": "11:00~16:00",
        "Sunday": "~",
        "Thursday": "11:00~20:00",
        "Tuesday": "11:00~20:00",
        "Wednesday": "11:00~19:00",
        "exam_part": "가정의학과",
        "holiday": "~",
        "instit_kind": "의원",
        "instit_nm": "365엠씨람스에스씨의원",
        "lat": "35.16719565",
        "lng": "129.1320372",
        "medical_instit_kind": "응급의료기관이외",
        "organ_loc": "2호선 센텀시티역 11번 출구",
        "regist_dt": "2020-11-23",
        "street_nm_addr": "부산광역시 해운대구 센텀2로 20, 센텀타워메디컬 1403호 (우동)",
        "sunday_oper_week": "",
        "tel": "1577-3653",
        "update_dt": "2020-11-25",
        "zip_code": "48060"
    },
    {
        "Friday": "09:30~20:00",
        "Monday": "09:30~20:00",
        "Saturday": "09:30~15:00",
        "Sunday": "~",
        "Thursday": "09:30~20:00",
        "Tuesday": "09:30~20:00",
        "Wednesday": "09:30~20:00",
        "exam_part": "",
        "holiday": "~",
        "instit_kind": "약국",
        "instit_nm": "호호약국",
        "lat": "35.22080677",
        "lng": "129.0881861",
        "medical_instit_kind": "응급의료기관이외",
        "organ_loc": "1호선 온천장역 4번출구",
        "regist_dt": "2020-11-09",
        "street_nm_addr": "부산광역시 금정구 동현로16번길 65, 1층 4호 (부곡동, 부곡영화맨션)",
        "sunday_oper_week": "",
        "tel": "051-517-7501",
        "update_dt": "2020-11-09",
        "zip_code": "46306"
    },
    {
        "Friday": "09:00~19:00",
        "Monday": "09:00~19:00",
        "Saturday": "09:00~19:00",
        "Sunday": "~",
        "Thursday": "09:00~19:00",
        "Tuesday": "09:00~19:00",
        "Wednesday": "09:00~19:00",
        "exam_part": "",
        "holiday": "09:00~19:00",
        "instit_kind": "약국",
        "instit_nm": "보리수약국",
        "lat": "35.17523373",
        "lng": "128.9849972",
        "medical_instit_kind": "응급의료기관이외",
        "organ_loc": "2호선 덕포역 4번출구",
        "regist_dt": "2020-11-09",
        "street_nm_addr": "부산광역시 사상구 사상로342번길 9, 2층 (덕포동)",
        "sunday_oper_week": "",
        "tel": "051-913-1141",
        "update_dt": "2020-11-09",
        "zip_code": "46945"
    },
    {
        "Friday": "09:30~19:00",
        "Monday": "09:30~19:00",
        "Saturday": "09:30~13:00",
        "Sunday": "~",
        "Thursday": "09:30~13:00",
        "Tuesday": "09:30~19:00",
        "Wednesday": "09:30~19:00",
        "exam_part": "사상체질과,침구과,한방내과,한방부인과,한방소아과,한방신경정신과,한방안이비인후피부과,한방재활의학과",
        "holiday": "~",
        "instit_kind": "한의원",
        "instit_nm": "가촌한의원",
        "lat": "35.21078933",
        "lng": "129.0825058",
        "medical_instit_kind": "응급의료기관이외",
        "organ_loc": "1호선 명륜역 2번출구",
        "regist_dt": "2020-11-05",
        "street_nm_addr": "부산광역시 동래구 명륜로 189-2, 2층 (명륜동)",
        "sunday_oper_week": "",
        "tel": "051-917-2175",
        "update_dt": "2020-12-23",
        "zip_code": "47742"
    },
    {
        "Friday": "09:00~18:30",
        "Monday": "09:00~18:30",
        "Saturday": "09:00~12:30",
        "Sunday": "~",
        "Thursday": "09:00~18:30",
        "Tuesday": "09:00~18:30",
        "Wednesday": "09:00~18:30",
        "exam_part": "",
        "holiday": "~",
        "instit_kind": "약국",
        "instit_nm": "열린약국",
        "lat": "35.17359727",
        "lng": "129.0694312",
        "medical_instit_kind": "응급의료기관이외",
        "organ_loc": "1호선 양정역 3번출구",
        "regist_dt": "2020-11-05",
        "street_nm_addr": "부산광역시 부산진구 동평로 410, 양정동근린생활시설 1층 (양정동)",
        "sunday_oper_week": "",
        "tel": "051-867-8841",
        "update_dt": "2020-12-07",
        "zip_code": "47213"
    },
    {
        "Friday": "09:00~18:00",
        "Monday": "09:00~18:00",
        "Saturday": "09:00~13:00",
        "Sunday": "~",
        "Thursday": "09:00~19:00",
        "Tuesday": "09:00~19:00",
        "Wednesday": "09:00~18:00",
        "exam_part": "구강내과,구강병리과,구강악안면방사선과,구강안면외과,소아치과,예방치과,치과보존과,치과보철과,치주과",
        "holiday": "~",
        "instit_kind": "치과의원",
        "instit_nm": "뿌리깊은이정근치과의원",
        "lat": "35.14817143",
        "lng": "129.1101975",
        "medical_instit_kind": "응급의료기관이외",
        "organ_loc": "2호선 금련산역 6번출구",
        "regist_dt": "2020-11-05",
        "street_nm_addr": "부산광역시 수영구 수영로 471, 오션스카이 남천 201호 (남천동)",
        "sunday_oper_week": "",
        "tel": "051-624-7528",
        "update_dt": "2020-11-05",
        "zip_code": "48265"
    },
    {
        "Friday": "09:00~18:00",
        "Monday": "09:00~18:00",
        "Saturday": "09:00~13:00",
        "Sunday": "~",
        "Thursday": "09:00~18:00",
        "Tuesday": "09:00~18:00",
        "Wednesday": "09:00~18:00",
        "exam_part": "내과,소아청소년과,신경과,이비인후과,재활의학과,정신건강의학과,정형외과",
        "holiday": "~",
        "instit_kind": "의원",
        "instit_nm": "부산달팽이 신경과,이비인후과 의원",
        "lat": "35.16591625",
        "lng": "129.1145004",
        "medical_instit_kind": "응급의료기관이외",
        "organ_loc": "2호선 수영역 10번출구",
        "regist_dt": "2020-11-05",
        "street_nm_addr": "부산광역시 수영구 수영로 675, 큐비 메디컬센터 6층 (광안동)",
        "sunday_oper_week": "",
        "tel": "051-784-7582",
        "update_dt": "2020-11-09",
        "zip_code": "48243"
    },
    {
        "Friday": "09:00~18:00",
        "Monday": "09:00~18:00",
        "Saturday": "09:00~13:00",
        "Sunday": "~",
        "Thursday": "09:00~18:00",
        "Tuesday": "09:00~18:00",
        "Wednesday": "09:00~18:00",
        "exam_part": "마취통증의학과,신경외과,정형외과",
        "holiday": "~",
        "instit_kind": "의원",
        "instit_nm": "명인마취통증의학과의원",
        "lat": "35.10658218",
        "lng": "128.9638108",
        "medical_instit_kind": "응급의료기관이외",
        "organ_loc": "1호선 하단역 1번출구",
        "regist_dt": "2020-11-05",
        "street_nm_addr": "부산광역시 사하구 낙동남로 1389, 4,5층 (하단동)",
        "sunday_oper_week": "",
        "tel": "051-204-8277",
        "update_dt": "2021-01-11",
        "zip_code": "49312"
    },
    {
        "Friday": "10:00~20:00",
        "Monday": "10:00~20:00",
        "Saturday": "10:00~20:00",
        "Sunday": "~",
        "Thursday": "10:00~20:00",
        "Tuesday": "10:00~20:00",
        "Wednesday": "10:00~20:00",
        "exam_part": "",
        "holiday": "~",
        "instit_kind": "약국",
        "instit_nm": "서문약국",
        "lat": "35.18932766",
        "lng": "129.0914989",
        "medical_instit_kind": "응급의료기관이외",
        "organ_loc": "",
        "regist_dt": "2020-11-02",
        "street_nm_addr": "부산광역시 연제구 연동로8번길 44, 1층 일부호 (연산동)",
        "sunday_oper_week": "",
        "tel": "",
        "update_dt": "2020-11-02",
        "zip_code": "47552"
    },
    {
        "Friday": "10:30~19:00",
        "Monday": "10:30~21:00",
        "Saturday": "10:30~15:00",
        "Sunday": "~",
        "Thursday": "10:30~19:00",
        "Tuesday": "10:30~19:00",
        "Wednesday": "10:30~21:00",
        "exam_part": "피부과",
        "holiday": "~",
        "instit_kind": "의원",
        "instit_nm": "일라스의원",
        "lat": "35.16694367",
        "lng": "129.1329558",
        "medical_instit_kind": "응급의료기관이외",
        "organ_loc": "2호선 센텀시티역 9번 출구",
        "regist_dt": "2020-11-02",
        "street_nm_addr": "부산광역시 해운대구 센텀2로 25, 센텀드림월드 1401호 (우동)",
        "sunday_oper_week": "",
        "tel": "051-710-0821",
        "update_dt": "2020-11-02",
        "zip_code": "48060"
    },
    {
        "Friday": "09:30~18:00",
        "Monday": "09:30~18:00",
        "Saturday": "09:30~13:00",
        "Sunday": "~",
        "Thursday": "09:30~18:00",
        "Tuesday": "09:30~18:00",
        "Wednesday": "09:30~18:00",
        "exam_part": "정신건강의학과",
        "holiday": "~",
        "instit_kind": "의원",
        "instit_nm": "윤혜원정신건강의학과의원",
        "lat": "35.13541842",
        "lng": "129.0921824",
        "medical_instit_kind": "응급의료기관이외",
        "organ_loc": "2호선 대연역 4번 출구",
        "regist_dt": "2020-10-30",
        "street_nm_addr": "부산광역시 남구 수영로 233, 민석빌딩 8층 (대연동)",
        "sunday_oper_week": "",
        "tel": "051-612-1335",
        "update_dt": "2020-10-30",
        "zip_code": "48445"
    },
    {
        "Friday": "09:30~20:00",
        "Monday": "09:30~20:00",
        "Saturday": "09:30~17:00",
        "Sunday": "~",
        "Thursday": "13:00~20:00",
        "Tuesday": "09:30~20:00",
        "Wednesday": "09:30~20:00",
        "exam_part": "",
        "holiday": "~",
        "instit_kind": "약국",
        "instit_nm": "시원약국",
        "lat": "35.13510721",
        "lng": "129.094702",
        "medical_instit_kind": "응급의료기관이외",
        "organ_loc": "2호선 대연역 1번출구",
        "regist_dt": "2020-10-26",
        "street_nm_addr": "부산광역시 남구 수영로 256-1, 1층 (대연동)",
        "sunday_oper_week": "",
        "tel": "051-612-7107",
        "update_dt": "2020-10-26",
        "zip_code": "48497"
    },
    {
        "Friday": "09:00~18:00",
        "Monday": "09:00~18:00",
        "Saturday": "09:00~18:00",
        "Sunday": "09:00~18:00",
        "Thursday": "09:00~18:00",
        "Tuesday": "09:00~18:00",
        "Wednesday": "09:00~18:00",
        "exam_part": "",
        "holiday": "~",
        "instit_kind": "약국",
        "instit_nm": "맘편한약국",
        "lat": "35.30153217",
        "lng": "129.2573269",
        "medical_instit_kind": "응급의료기관이외",
        "organ_loc": "칠암문중마을 경계지 교차로 근처",
        "regist_dt": "2020-10-26",
        "street_nm_addr": "부산광역시 기장군 일광면 일광로 667, 1층 103호",
        "sunday_oper_week": "1 2 3 4 5",
        "tel": "0507-1441-8918",
        "update_dt": "2020-11-05",
        "zip_code": "46040"
    },
    {
        "Friday": "09:00~18:00",
        "Monday": "09:00~18:00",
        "Saturday": "09:00~15:00",
        "Sunday": "~",
        "Thursday": "09:00~18:00",
        "Tuesday": "09:00~18:00",
        "Wednesday": "09:00~18:00",
        "exam_part": "",
        "holiday": "~",
        "instit_kind": "약국",
        "instit_nm": "다정한약국",
        "lat": "35.1033693",
        "lng": "129.0257126",
        "medical_instit_kind": "응급의료기관이외",
        "organ_loc": "버스정류장: 보수동 책방골목앞",
        "regist_dt": "2020-10-26",
        "street_nm_addr": "부산광역시 중구 대청로53번길 7, 1층 (보수동1가)",
        "sunday_oper_week": "",
        "tel": "051-242-2257",
        "update_dt": "2020-10-26",
        "zip_code": "48962"
    },
    {
        "Friday": "09:30~18:30",
        "Monday": "09:30~18:30",
        "Saturday": "09:30~14:00",
        "Sunday": "~",
        "Thursday": "09:30~18:30",
        "Tuesday": "09:30~18:30",
        "Wednesday": "09:30~14:00",
        "exam_part": "구강내과,구강병리과,구강악안면방사선과,구강안면외과,소아치과,예방치과,치과교정과,치과보존과,치과보철과,치주과",
        "holiday": "~",
        "instit_kind": "치과의원",
        "instit_nm": "디오스치과의원",
        "lat": "35.14300488",
        "lng": "129.1084044",
        "medical_instit_kind": "응급의료기관이외",
        "organ_loc": "2호선 남천역 2번출구",
        "regist_dt": "2020-10-26",
        "street_nm_addr": "부산광역시 수영구 수영로 411, 글로리 2층 (남천동)",
        "sunday_oper_week": "",
        "tel": "051-791-0555",
        "update_dt": "2020-10-26",
        "zip_code": "48316"
    },
    {
        "Friday": "10:00~18:30",
        "Monday": "10:00~18:30",
        "Saturday": "10:00~14:00",
        "Sunday": "~",
        "Thursday": "10:00~18:30",
        "Tuesday": "10:00~18:30",
        "Wednesday": "16:00~21:00",
        "exam_part": "신경과,정신건강의학과",
        "holiday": "~",
        "instit_kind": "의원",
        "instit_nm": "삼성공감정신건강의학과의원",
        "lat": "35.16986881",
        "lng": "129.1324585",
        "medical_instit_kind": "응급의료기관이외",
        "organ_loc": "2호선 센텀시티역 2번출구",
        "regist_dt": "2020-10-26",
        "street_nm_addr": "부산광역시 해운대구 센텀동로 9, 221호 (우동, 트럼프월드센텀아파트)",
        "sunday_oper_week": "",
        "tel": "051-746-3302",
        "update_dt": "2020-10-26",
        "zip_code": "48059"
    },
    {
        "Friday": "08:30~18:00",
        "Monday": "08:30~18:00",
        "Saturday": "08:30~13:00",
        "Sunday": "~",
        "Thursday": "08:30~18:00",
        "Tuesday": "08:30~18:00",
        "Wednesday": "08:30~18:00",
        "exam_part": "사상체질과,침구과,한방내과,한방부인과,한방소아과,한방신경정신과,한방안이비인후피부과,한방응급과,한방재활의학과",
        "holiday": "08:30~13:00",
        "instit_kind": "한의원",
        "instit_nm": "더큰한의원",
        "lat": "35.21395245",
        "lng": "129.0362968",
        "medical_instit_kind": "응급의료기관이외",
        "organ_loc": "3호선 만덕역 4번출구",
        "regist_dt": "2020-10-22",
        "street_nm_addr": "부산광역시 북구 만덕1로 9, 세영빌딩 2~3층 (만덕동)",
        "sunday_oper_week": "",
        "tel": "051-338-1075",
        "update_dt": "2020-10-22",
        "zip_code": "46561"
    },
    {
        "Friday": "09:00~17:30",
        "Monday": "09:00~17:30",
        "Saturday": "~",
        "Sunday": "~",
        "Thursday": "09:00~17:30",
        "Tuesday": "09:00~17:30",
        "Wednesday": "09:00~17:30",
        "exam_part": "가정의학과,내과,사상체질과,침구과,한방내과",
        "holiday": "~",
        "instit_kind": "한방병원",
        "instit_nm": "다남한방병원",
        "lat": "35.32228833",
        "lng": "129.1788822",
        "medical_instit_kind": "응급의료기관이외",
        "organ_loc": "버스정류장: 히어로 테마파크 앞",
        "regist_dt": "2020-10-22",
        "street_nm_addr": "부산광역시 기장군 정관읍 정관8로 28, 6층",
        "sunday_oper_week": "",
        "tel": "051-728-3311",
        "update_dt": "2021-01-12",
        "zip_code": "46015"
    },
    {
        "Friday": "11:00~21:00",
        "Monday": "11:00~21:00",
        "Saturday": "11:00~21:00",
        "Sunday": "11:00~21:00",
        "Thursday": "11:00~21:00",
        "Tuesday": "11:00~21:00",
        "Wednesday": "11:00~21:00",
        "exam_part": "",
        "holiday": "~",
        "instit_kind": "약국",
        "instit_nm": "동부산약국",
        "lat": "35.19221051",
        "lng": "129.2127825",
        "medical_instit_kind": "응급의료기관이외",
        "organ_loc": "롯데마트안",
        "regist_dt": "2020-10-22",
        "street_nm_addr": "부산광역시 기장군 기장읍 기장해안로 147, 롯데몰 동부산점 롯데마트 2층",
        "sunday_oper_week": "1 3 5",
        "tel": "051-901-2160",
        "update_dt": "2021-01-27",
        "zip_code": "46084"
    },
    {
        "Friday": "10:00~19:00",
        "Monday": "10:00~19:00",
        "Saturday": "10:00~17:00",
        "Sunday": "10:00~17:00",
        "Thursday": "10:00~19:00",
        "Tuesday": "10:00~19:00",
        "Wednesday": "10:00~19:00",
        "exam_part": "성형외과",
        "holiday": "~",
        "instit_kind": "의원",
        "instit_nm": "아이노유성형외과의원",
        "lat": "35.15806536",
        "lng": "129.057231",
        "medical_instit_kind": "응급의료기관이외",
        "organ_loc": "2호선 9번출구",
        "regist_dt": "2020-10-22",
        "street_nm_addr": "부산광역시 부산진구 가야대로 783, 14층 (부전동)",
        "sunday_oper_week": "1 2 3 4 5",
        "tel": "051-809-9922",
        "update_dt": "2020-10-22",
        "zip_code": "47257"
    },
    {
        "Friday": "09:00~18:00",
        "Monday": "09:00~18:00",
        "Saturday": "09:00~14:00",
        "Sunday": "~",
        "Thursday": "09:00~18:00",
        "Tuesday": "09:00~18:00",
        "Wednesday": "09:00~18:00",
        "exam_part": "내과,마취통증의학과,신경외과,재활의학과,정형외과",
        "holiday": "~",
        "instit_kind": "의원",
        "instit_nm": "기장연합신경외과마취통증의학과의원",
        "lat": "35.24493494",
        "lng": "129.2142382",
        "medical_instit_kind": "응급의료기관이외",
        "organ_loc": "동해기장역 1번 출구",
        "regist_dt": "2020-10-22",
        "street_nm_addr": "부산광역시 기장군 기장읍 읍내로 92, 우리은행 5층",
        "sunday_oper_week": "",
        "tel": "051-715-0225",
        "update_dt": "2020-10-22",
        "zip_code": "46066"
    },
    {
        "Friday": "09:00~18:00",
        "Monday": "09:00~18:00",
        "Saturday": "09:00~13:00",
        "Sunday": "~",
        "Thursday": "09:00~18:00",
        "Tuesday": "09:00~18:00",
        "Wednesday": "09:00~18:00",
        "exam_part": "가정의학과,마취통증의학과,신경외과,재활의학과,정형외과",
        "holiday": "09:00~12:00",
        "instit_kind": "의원",
        "instit_nm": "참좋은정형외과의원",
        "lat": "35.18586867",
        "lng": "128.9907034",
        "medical_instit_kind": "응급의료기관이외",
        "organ_loc": "2호선 모라역 2번출구",
        "regist_dt": "2020-10-19",
        "street_nm_addr": "부산광역시 사상구 백양대로 893, 궁전빌딩 402호 (모라동)",
        "sunday_oper_week": "",
        "tel": "051-312-7582",
        "update_dt": "2020-11-30",
        "zip_code": "46930"
    },
    {
        "Friday": "09:00~19:00",
        "Monday": "09:00~19:00",
        "Saturday": "09:00~16:00",
        "Sunday": "~",
        "Thursday": "09:00~19:00",
        "Tuesday": "09:00~19:00",
        "Wednesday": "09:00~19:00",
        "exam_part": "",
        "holiday": "~",
        "instit_kind": "약국",
        "instit_nm": "큐비약국",
        "lat": "35.16591625",
        "lng": "129.1145004",
        "medical_instit_kind": "응급의료기관이외",
        "organ_loc": "2호선 수영역 10번출구",
        "regist_dt": "2020-10-15",
        "street_nm_addr": "부산광역시 수영구 수영로 675, 101호 (광안동)",
        "sunday_oper_week": "",
        "tel": "051-752-4200",
        "update_dt": "2020-10-15",
        "zip_code": "48243"
    },
    {
        "Friday": "09:00~18:00",
        "Monday": "09:00~18:00",
        "Saturday": "09:00~13:00",
        "Sunday": "~",
        "Thursday": "09:00~18:00",
        "Tuesday": "09:00~18:00",
        "Wednesday": "09:00~18:00",
        "exam_part": "",
        "holiday": "~",
        "instit_kind": "약국",
        "instit_nm": "진심약국",
        "lat": "35.12459949",
        "lng": "129.044433",
        "medical_instit_kind": "응급의료기관이외",
        "organ_loc": "",
        "regist_dt": "2020-10-15",
        "street_nm_addr": "부산광역시 동구 중앙대로 313, 세정빌딩 1층 (초량동)",
        "sunday_oper_week": "",
        "tel": "051-467-2100",
        "update_dt": "2020-10-15",
        "zip_code": "48792"
    },
    {
        "Friday": "09:00~18:30",
        "Monday": "09:00~18:30",
        "Saturday": "09:00~13:00",
        "Sunday": "~",
        "Thursday": "09:00~18:30",
        "Tuesday": "09:00~18:30",
        "Wednesday": "09:00~18:30",
        "exam_part": "비뇨의학과",
        "holiday": "~",
        "instit_kind": "의원",
        "instit_nm": "장산닥터남비뇨의학과의원",
        "lat": "35.17097853",
        "lng": "129.1776682",
        "medical_instit_kind": "응급의료기관이외",
        "organ_loc": "2호선 장산역 2번출구",
        "regist_dt": "2020-10-15",
        "street_nm_addr": "부산광역시 해운대구 세실로 64, 310~312호 (좌동, 화목데파트)",
        "sunday_oper_week": "",
        "tel": "051-702-5825",
        "update_dt": "2020-10-15",
        "zip_code": "48107"
    },
    {
        "Friday": "09:00~18:00",
        "Monday": "09:00~18:00",
        "Saturday": "09:00~13:00",
        "Sunday": "~",
        "Thursday": "09:00~20:00",
        "Tuesday": "09:00~20:00",
        "Wednesday": "09:00~18:00",
        "exam_part": "내과,마취통증의학과,정형외과",
        "holiday": "~",
        "instit_kind": "의원",
        "instit_nm": "류마통내과의원",
        "lat": "35.26545263",
        "lng": "129.0921135",
        "medical_instit_kind": "응급의료기관이외",
        "organ_loc": "1호선 남산역 5번출구",
        "regist_dt": "2020-10-15",
        "street_nm_addr": "부산광역시 금정구 중앙대로 2027, 새생명빌딩 3층 (남산동)",
        "sunday_oper_week": "",
        "tel": "051-715-7050",
        "update_dt": "2020-10-19",
        "zip_code": "46224"
    },
    {
        "Friday": "08:30~18:30",
        "Monday": "08:30~18:30",
        "Saturday": "08:30~13:00",
        "Sunday": "~",
        "Thursday": "08:30~13:00",
        "Tuesday": "08:30~18:30",
        "Wednesday": "08:30~18:30",
        "exam_part": "내과",
        "holiday": "~",
        "instit_kind": "의원",
        "instit_nm": "위아래내과의원",
        "lat": "35.0649693",
        "lng": "128.9799961",
        "medical_instit_kind": "응급의료기관이외",
        "organ_loc": "1호선 낫개역 4번출구",
        "regist_dt": "2020-10-13",
        "street_nm_addr": "부산광역시 사하구 다대로 425, 5층 (다대동)",
        "sunday_oper_week": "",
        "tel": "051-715-3500",
        "update_dt": "2020-10-13",
        "zip_code": "49518"
    },
    {
        "Friday": "09:00~18:30",
        "Monday": "09:00~18:30",
        "Saturday": "09:00~13:30",
        "Sunday": "~",
        "Thursday": "09:00~20:00",
        "Tuesday": "09:00~18:30",
        "Wednesday": "09:00~18:30",
        "exam_part": "마취통증의학과,신경외과,재활의학과,정형외과",
        "holiday": "~",
        "instit_kind": "의원",
        "instit_nm": "고든정형외과의원",
        "lat": "35.19796799",
        "lng": "129.0605377",
        "medical_instit_kind": "응급의료기관이외",
        "organ_loc": "3호선 사직역 3번출구",
        "regist_dt": "2020-10-13",
        "street_nm_addr": "부산광역시 동래구 사직북로 24, 가람빌딩 8층 (사직동)",
        "sunday_oper_week": "",
        "tel": "051-507-8878",
        "update_dt": "2020-10-26",
        "zip_code": "47859"
    },
    {
        "Friday": "09:00~19:00",
        "Monday": "09:00~19:00",
        "Saturday": "09:00~14:00",
        "Sunday": "~",
        "Thursday": "09:00~19:00",
        "Tuesday": "09:00~19:00",
        "Wednesday": "09:00~19:00",
        "exam_part": "사상체질과,침구과,한방내과,한방부인과,한방소아과,한방신경정신과,한방안이비인후피부과,한방재활의학과",
        "holiday": "~",
        "instit_kind": "한의원",
        "instit_nm": "인향한의원",
        "lat": "35.21430377",
        "lng": "129.0363232",
        "medical_instit_kind": "응급의료기관이외",
        "organ_loc": "3호선 만덕역 4번출구",
        "regist_dt": "2020-10-05",
        "street_nm_addr": "부산광역시 북구 만덕1로10번길 6, 2층 (만덕동)",
        "sunday_oper_week": "",
        "tel": "051-337-6859",
        "update_dt": "2020-12-16",
        "zip_code": "46557"
    },
    {
        "Friday": "09:00~18:00",
        "Monday": "09:00~18:00",
        "Saturday": "09:00~17:00",
        "Sunday": "~",
        "Thursday": "09:00~18:00",
        "Tuesday": "09:00~18:00",
        "Wednesday": "09:00~18:00",
        "exam_part": "",
        "holiday": "~",
        "instit_kind": "약국",
        "instit_nm": "서부산약국",
        "lat": "35.16262351",
        "lng": "128.9849547",
        "medical_instit_kind": "응급의료기관이외",
        "organ_loc": "2호선 사상역 4번출구",
        "regist_dt": "2020-09-28",
        "street_nm_addr": "부산광역시 사상구 광장로 77 (괘법동)",
        "sunday_oper_week": "",
        "tel": "070-4038-9826",
        "update_dt": "2020-09-28",
        "zip_code": "46968"
    },
    {
        "Friday": "08:30~21:00",
        "Monday": "08:30~21:00",
        "Saturday": "10:00~21:00",
        "Sunday": "08:30~15:00",
        "Thursday": "08:30~21:00",
        "Tuesday": "08:30~21:00",
        "Wednesday": "08:30~21:00",
        "exam_part": "",
        "holiday": "~",
        "instit_kind": "약국",
        "instit_nm": "부산METRO약국",
        "lat": "35.22961181",
        "lng": "129.0893474",
        "medical_instit_kind": "응급의료기관이외",
        "organ_loc": "부산대지하철역 내 위치",
        "regist_dt": "2020-09-28",
        "street_nm_addr": "부산광역시 금정구 장전온천천로 48, 부산대지하철역 1층 (장전동)",
        "sunday_oper_week": "1 2 3 4 5",
        "tel": "051-000-0000",
        "update_dt": "2020-12-23",
        "zip_code": "46291"
    },
    {
        "Friday": "09:30~18:00",
        "Monday": "09:30~18:00",
        "Saturday": "09:30~14:00",
        "Sunday": "~",
        "Thursday": "09:30~18:00",
        "Tuesday": "09:30~18:00",
        "Wednesday": "09:30~18:00",
        "exam_part": "가정의학과,내과,외과,흉부외과",
        "holiday": "~",
        "instit_kind": "의원",
        "instit_nm": "덕천바른흉부외과의원",
        "lat": "35.21072315",
        "lng": "129.0067005",
        "medical_instit_kind": "응급의료기관이외",
        "organ_loc": "3호선 덕천역 12번출구",
        "regist_dt": "2020-09-28",
        "street_nm_addr": "부산광역시 북구 만덕대로 15, 4층 (덕천동)",
        "sunday_oper_week": "",
        "tel": "051-711-4288",
        "update_dt": "2020-09-28",
        "zip_code": "46548"
    },
    {
        "Friday": "09:30~18:00",
        "Monday": "09:30~18:00",
        "Saturday": "09:30~14:00",
        "Sunday": "~",
        "Thursday": "09:30~18:00",
        "Tuesday": "09:30~18:00",
        "Wednesday": "09:30~18:00",
        "exam_part": "구강내과,구강병리과,구강악안면방사선과,구강안면외과,소아치과,예방치과,치과교정과,치과보존과,치과보철과,치주과",
        "holiday": "~",
        "instit_kind": "치과의원",
        "instit_nm": "해운대감동치과의원",
        "lat": "35.17376574",
        "lng": "129.1811665",
        "medical_instit_kind": "응급의료기관이외",
        "organ_loc": "2호선 장산역 2번출구",
        "regist_dt": "2020-09-25",
        "street_nm_addr": "부산광역시 해운대구 좌동순환로 247, 유안빌딩 3층 (좌동)",
        "sunday_oper_week": "",
        "tel": "051-703-0703",
        "update_dt": "2020-12-23",
        "zip_code": "48108"
    },
    {
        "Friday": "09:00~18:00",
        "Monday": "09:00~18:00",
        "Saturday": "09:00~13:00",
        "Sunday": "~",
        "Thursday": "09:00~18:00",
        "Tuesday": "09:00~18:00",
        "Wednesday": "09:00~18:00",
        "exam_part": "",
        "holiday": "~",
        "instit_kind": "약국",
        "instit_nm": "태평양약국",
        "lat": "35.20578993",
        "lng": "129.077091",
        "medical_instit_kind": "응급의료기관이외",
        "organ_loc": "4호선 동래역 5번출구",
        "regist_dt": "2020-09-17",
        "street_nm_addr": "부산광역시 동래구 충렬대로155번길 19, 1층 일부호 (온천동)",
        "sunday_oper_week": "",
        "tel": "051-710-5177",
        "update_dt": "2020-09-17",
        "zip_code": "47734"
    },
    {
        "Friday": "09:00~19:00",
        "Monday": "09:00~19:00",
        "Saturday": "09:00~14:00",
        "Sunday": "~",
        "Thursday": "09:00~19:00",
        "Tuesday": "09:00~19:00",
        "Wednesday": "09:00~19:00",
        "exam_part": "",
        "holiday": "~",
        "instit_kind": "약국",
        "instit_nm": "범어약국",
        "lat": "35.27394125",
        "lng": "129.0923705",
        "medical_instit_kind": "응급의료기관이외",
        "organ_loc": "1호선 범어사역 7번출구",
        "regist_dt": "2020-09-17",
        "street_nm_addr": "부산광역시 금정구 청룡예전로 2, 경신빌딩 1층 (청룡동)",
        "sunday_oper_week": "",
        "tel": "051-508-7228",
        "update_dt": "2020-12-23",
        "zip_code": "46218"
    },
    {
        "Friday": "09:00~20:00",
        "Monday": "09:00~20:00",
        "Saturday": "09:00~19:00",
        "Sunday": "~",
        "Thursday": "09:00~20:00",
        "Tuesday": "09:00~20:00",
        "Wednesday": "09:00~20:00",
        "exam_part": "",
        "holiday": "~",
        "instit_kind": "약국",
        "instit_nm": "금파약국",
        "lat": "35.18754233",
        "lng": "129.1074286",
        "medical_instit_kind": "응급의료기관이외",
        "organ_loc": "버스정류장: 태광아파트 앞",
        "regist_dt": "2020-09-17",
        "street_nm_addr": "부산광역시 연제구 과정로 180, 1층 102호 (연산동)",
        "sunday_oper_week": "",
        "tel": "051-758-5566",
        "update_dt": "2020-09-17",
        "zip_code": "47569"
    },
    {
        "Friday": "09:00~18:00",
        "Monday": "09:00~18:00",
        "Saturday": "09:00~12:30",
        "Sunday": "~",
        "Thursday": "09:00~18:00",
        "Tuesday": "09:00~18:00",
        "Wednesday": "09:00~18:00",
        "exam_part": "가정의학과,내과,비뇨의학과,성형외과,소아청소년과,외과,이비인후과,피부과",
        "holiday": "~",
        "instit_kind": "의원",
        "instit_nm": "광안웰빙의원",
        "lat": "35.1630038",
        "lng": "129.1087199",
        "medical_instit_kind": "응급의료기관이외",
        "organ_loc": "2호선 수영역 14번 출구",
        "regist_dt": "2020-09-17",
        "street_nm_addr": "부산광역시 수영구 광일로 49, 109동 102호 (광안동, 비치그린아파트)",
        "sunday_oper_week": "",
        "tel": "051-754-7786",
        "update_dt": "2020-12-21",
        "zip_code": "48250"
    },
    {
        "Friday": "10:00~19:00",
        "Monday": "10:00~21:00",
        "Saturday": "09:00~14:00",
        "Sunday": "~",
        "Thursday": "10:00~21:00",
        "Tuesday": "10:00~19:00",
        "Wednesday": "10:00~21:00",
        "exam_part": "사상체질과,침구과,한방내과,한방부인과,한방소아과,한방신경정신과,한방안이비인후피부과,한방재활의학과",
        "holiday": "~",
        "instit_kind": "한의원",
        "instit_nm": "미소로한의원",
        "lat": "35.15802126",
        "lng": "129.0571207",
        "medical_instit_kind": "응급의료기관이외",
        "organ_loc": "2호선 서면역 9번출구",
        "regist_dt": "2020-09-15",
        "street_nm_addr": "부산광역시 부산진구 가야대로 781-1, 3층 (부전동)",
        "sunday_oper_week": "",
        "tel": "051-817-3515",
        "update_dt": "2020-12-28",
        "zip_code": "47257"
    },
    {
        "Friday": "09:30~20:00",
        "Monday": "09:30~20:00",
        "Saturday": "09:30~13:00",
        "Sunday": "09:30~13:00",
        "Thursday": "09:30~13:00",
        "Tuesday": "09:30~20:00",
        "Wednesday": "09:30~20:00",
        "exam_part": "사상체질과,침구과,한방내과,한방부인과,한방소아과,한방신경정신과,한방안이비인후피부과,한방응급과,한방재활의학과",
        "holiday": "09:30~13:00",
        "instit_kind": "한의원",
        "instit_nm": "365부부한의원",
        "lat": "35.26630446",
        "lng": "129.2260202",
        "medical_instit_kind": "응급의료기관이외",
        "organ_loc": "동해 일광역 2번출구",
        "regist_dt": "2020-09-15",
        "street_nm_addr": "부산광역시 기장군 일광면 해빛로 17, 201호",
        "sunday_oper_week": "1 2 3 4 5",
        "tel": "051-724-7633",
        "update_dt": "2020-09-15",
        "zip_code": "46048"
    },
    {
        "Friday": "08:30~20:00",
        "Monday": "08:30~20:00",
        "Saturday": "08:30~20:00",
        "Sunday": "~",
        "Thursday": "08:30~20:00",
        "Tuesday": "08:30~20:00",
        "Wednesday": "08:30~20:00",
        "exam_part": "",
        "holiday": "~",
        "instit_kind": "약국",
        "instit_nm": "싱글벙글약국",
        "lat": "35.21033221",
        "lng": "129.007102",
        "medical_instit_kind": "응급의료기관이외",
        "organ_loc": "3호선 덕천역 9번출구",
        "regist_dt": "2020-09-07",
        "street_nm_addr": "부산광역시 북구 만덕대로 18, 금샘빌딩 106호 (덕천동)",
        "sunday_oper_week": "",
        "tel": "051-338-8922",
        "update_dt": "2020-09-07",
        "zip_code": "46576"
    },
    {
        "Friday": "09:00~18:00",
        "Monday": "09:00~18:00",
        "Saturday": "09:00~13:00",
        "Sunday": "~",
        "Thursday": "09:00~18:00",
        "Tuesday": "09:00~18:00",
        "Wednesday": "09:00~18:00",
        "exam_part": "",
        "holiday": "~",
        "instit_kind": "약국",
        "instit_nm": "네온우리약국",
        "lat": "35.17053918",
        "lng": "129.0768119",
        "medical_instit_kind": "응급의료기관이외",
        "organ_loc": "",
        "regist_dt": "2020-09-07",
        "street_nm_addr": "부산광역시 부산진구 양정로 61, 1,2층 (양정동)",
        "sunday_oper_week": "",
        "tel": "051-911-4954",
        "update_dt": "2020-09-07",
        "zip_code": "47224"
    },
    {
        "Friday": "09:00~18:00",
        "Monday": "09:00~18:00",
        "Saturday": "09:00~12:30",
        "Sunday": "~",
        "Thursday": "09:00~18:00",
        "Tuesday": "09:00~18:00",
        "Wednesday": "09:00~18:00",
        "exam_part": "구강내과,구강병리과,구강악안면방사선과,구강안면외과,소아치과,예방치과,치과교정과,치과보존과,치과보철과,치주과",
        "holiday": "~",
        "instit_kind": "치과의원",
        "instit_nm": "남주치과의원",
        "lat": "35.26630446",
        "lng": "129.2260202",
        "medical_instit_kind": "응급의료기관이외",
        "organ_loc": "",
        "regist_dt": "2020-09-07",
        "street_nm_addr": "부산광역시 기장군 일광면 해빛로 17, 5층 501,502호 일부호",
        "sunday_oper_week": "",
        "tel": "051-723-2804",
        "update_dt": "2020-09-07",
        "zip_code": "46048"
    },
    {
        "Friday": "09:00~20:00",
        "Monday": "09:00~20:00",
        "Saturday": "09:30~14:30",
        "Sunday": "~",
        "Thursday": "09:00~18:00",
        "Tuesday": "09:00~18:00",
        "Wednesday": "09:00~20:00",
        "exam_part": "마취통증의학과,신경외과,재활의학과,정형외과,피부과",
        "holiday": "~",
        "instit_kind": "의원",
        "instit_nm": "서울스카이재활의학과의원",
        "lat": "35.13756007",
        "lng": "129.1015382",
        "medical_instit_kind": "응급의료기관이외",
        "organ_loc": "2호선 경성대역 1번출구",
        "regist_dt": "2020-09-07",
        "street_nm_addr": "부산광역시 남구 수영로 324, 2층 201호 (대연동, 리마크빌 대연)",
        "sunday_oper_week": "",
        "tel": "051-626-9111",
        "update_dt": "2020-11-23",
        "zip_code": "48508"
    },
    {
        "Friday": "10:00~19:00",
        "Monday": "10:00~19:00",
        "Saturday": "10:00~14:00",
        "Sunday": "~",
        "Thursday": "10:00~14:00",
        "Tuesday": "10:00~19:00",
        "Wednesday": "10:00~20:30",
        "exam_part": "사상체질과,침구과,한방내과,한방부인과,한방소아과,한방신경정신과,한방안이비인후피부과,한방재활의학과",
        "holiday": "~",
        "instit_kind": "한의원",
        "instit_nm": "위강한의원",
        "lat": "35.16567079",
        "lng": "129.1682284",
        "medical_instit_kind": "응급의료기관이외",
        "organ_loc": "2호선 중동역 7번출구",
        "regist_dt": "2020-09-02",
        "street_nm_addr": "부산광역시 해운대구 좌동순환로 505, 센트럴메디타워 3층 301호 (중동)",
        "sunday_oper_week": "",
        "tel": "051-731-7582",
        "update_dt": "2020-11-16",
        "zip_code": "48096"
    },
    {
        "Friday": "09:00~21:00",
        "Monday": "09:00~21:00",
        "Saturday": "09:00~18:30",
        "Sunday": "09:00~18:30",
        "Thursday": "09:00~21:00",
        "Tuesday": "09:00~21:00",
        "Wednesday": "09:00~21:00",
        "exam_part": "",
        "holiday": "09:00~18:30",
        "instit_kind": "약국",
        "instit_nm": "호호약국",
        "lat": "35.08116028",
        "lng": "128.9032876",
        "medical_instit_kind": "응급의료기관이외",
        "organ_loc": "버스정류장: 롯데캐슬아파트 앞",
        "regist_dt": "2020-09-02",
        "street_nm_addr": "부산광역시 강서구 명지오션시티4로 88, 1층 102호 (명지동)",
        "sunday_oper_week": "1 2 3 4 5",
        "tel": "051-202-5334",
        "update_dt": "2020-11-10",
        "zip_code": "46765"
    },
    {
        "Friday": "09:00~19:00",
        "Monday": "09:00~19:00",
        "Saturday": "~",
        "Sunday": "~",
        "Thursday": "09:00~19:00",
        "Tuesday": "09:00~19:00",
        "Wednesday": "09:00~19:00",
        "exam_part": "",
        "holiday": "~",
        "instit_kind": "약국",
        "instit_nm": "정문약국",
        "lat": "35.15058505",
        "lng": "129.0074288",
        "medical_instit_kind": "응급의료기관이외",
        "organ_loc": "좋은삼은삼선병원 앞",
        "regist_dt": "2020-09-02",
        "street_nm_addr": "부산광역시 사상구 가야대로 318 (주례동)",
        "sunday_oper_week": "",
        "tel": "051-316-0508",
        "update_dt": "2020-09-02",
        "zip_code": "47007"
    },
    {
        "Friday": "09:00~19:00",
        "Monday": "09:00~19:00",
        "Saturday": "09:00~14:00",
        "Sunday": "~",
        "Thursday": "09:00~19:00",
        "Tuesday": "09:00~19:00",
        "Wednesday": "09:00~19:00",
        "exam_part": "",
        "holiday": "~",
        "instit_kind": "약국",
        "instit_nm": "원약국",
        "lat": "35.22636131",
        "lng": "129.0122107",
        "medical_instit_kind": "응급의료기관이외",
        "organ_loc": "수정역 4번 출구",
        "regist_dt": "2020-09-02",
        "street_nm_addr": "부산광역시 북구 금곡대로 166, 상가동 3층 316호 (화명동, 롯데캐슬카이저)",
        "sunday_oper_week": "",
        "tel": "051-363-4555",
        "update_dt": "2020-09-02",
        "zip_code": "46539"
    },
    {
        "Friday": "09:00~18:00",
        "Monday": "09:00~18:00",
        "Saturday": "~",
        "Sunday": "~",
        "Thursday": "09:00~18:00",
        "Tuesday": "09:00~18:00",
        "Wednesday": "09:00~18:00",
        "exam_part": "",
        "holiday": "~",
        "instit_kind": "약국",
        "instit_nm": "서울약국",
        "lat": "35.19687507",
        "lng": "129.1040964",
        "medical_instit_kind": "응급의료기관이외",
        "organ_loc": "2호선 동해안락역 2번출구",
        "regist_dt": "2020-09-02",
        "street_nm_addr": "부산광역시 동래구 충렬대로 417, 1층 102호 (안락동)",
        "sunday_oper_week": "",
        "tel": "051-914-0050",
        "update_dt": "2020-09-02",
        "zip_code": "47796"
    },
    {
        "Friday": "09:00~18:00",
        "Monday": "09:00~18:00",
        "Saturday": "09:00~13:00",
        "Sunday": "~",
        "Thursday": "09:00~18:00",
        "Tuesday": "09:00~18:00",
        "Wednesday": "09:00~18:00",
        "exam_part": "",
        "holiday": "~",
        "instit_kind": "약국",
        "instit_nm": "새동의약국",
        "lat": "35.17079547",
        "lng": "129.0773861",
        "medical_instit_kind": "응급의료기관이외",
        "organ_loc": "1호선 양정역 4번출구",
        "regist_dt": "2020-09-02",
        "street_nm_addr": "부산광역시 부산진구 양정로 63, 원각사 2,3층 (양정동)",
        "sunday_oper_week": "",
        "tel": "051-911-0501",
        "update_dt": "2020-09-02",
        "zip_code": "47225"
    }
]